lime_comb/__init__.py
lime_comb/api.py
lime_comb/auth/__init__.py
lime_comb/auth/google.py
lime_comb/commands/__init__.py
lime_comb/commands/base.py
lime_comb/commands/common.py
lime_comb/commands/config.py
lime_comb/commands/decrypt.py
lime_comb/commands/encrypt.py
lime_comb/commands/keys.py
lime_comb/config.py
lime_comb/gpg/__init__.py
lime_comb/logger/__init__.py
lime_comb/logger/logger.py
lime_comb/main.py
lime_comb/validators/__init__.py
lime_comb/validators/bool.py
lime_comb/validators/email.py
lime_comb/validators/file.py
lime_comb-0.0.19.dist-info/entry_points.txt
lime_comb-0.0.19.dist-info/WHEEL
lime_comb-0.0.19.dist-info/METADATA
lime_comb-0.0.19.dist-info/RECORD
