Metadata-Version: 2.1
Name: lime-comb
Version: 0.0.19
Summary: lime-comb cli
Author: Marcin Niemira
Author-email: marcin.niemira@gmail.com
Requires-Python: >=3.7,<4.0
Classifier: Programming Language :: Python :: 3
Classifier: Programming Language :: Python :: 3.7
Classifier: Programming Language :: Python :: 3.8
Requires-Dist: appdirs (>=1.4.3,<2.0.0)
Requires-Dist: black (>=19.10b0,<20.0)
Requires-Dist: email-validator (>=1.0.5,<2.0.0)
Requires-Dist: email_validator (>=1.0.5,<2.0.0)
Requires-Dist: google-auth (>=1.10.0,<2.0.0)
Requires-Dist: google-auth-oauthlib (>=0.4.1,<0.5.0)
Requires-Dist: gql (>=0.4.0,<0.5.0)
Requires-Dist: grpcio-gcp (>=0.2.2,<0.3.0)
Requires-Dist: mock (>=4.0.1,<5.0.0)
Requires-Dist: password_generator (>=0.1.0,<0.2.0)
Requires-Dist: pyperclip (>=1.7.0,<2.0.0)
Requires-Dist: python-gnupg (>=0.4.5,<0.5.0)
Requires-Dist: pyyaml (>=5.3,<6.0)
Requires-Dist: requests (>=2.23.0,<3.0.0)
Requires-Dist: requests_mock (>=1.7.0,<2.0.0)
Requires-Dist: requests_oauthlib (>=1.3.0,<2.0.0)
Requires-Dist: semver (>=2.9.1,<3.0.0)
Requires-Dist: tabulate (>=0.8.6,<0.9.0)
Requires-Dist: tqdm (>=4.41.1,<5.0.0)
Project-URL: Bug Tracker, https://github.com/n0npax/lime-comb
Project-URL: documentation, https://github.com/n0npax/lime-comb
Project-URL: homepage, https://lime-comb.web.app/
Project-URL: repository, https://github.com/n0npax/lime-comb
